ruffless/__init__.py
ruffless-0.0.1.dist-info/METADATA
ruffless-0.0.1.dist-info/WHEEL
ruffless-0.0.1.dist-info/top_level.txt
ruffless-0.0.1.dist-info/RECORD
