Metadata-Version: 2.4
Name: ruffless
Version: 0.0.1
Summary: Universal baseline for your favourite linter
Author-email: Alexey Sidorov <ereon.dev@gmail.com>
License: MIT
Requires-Python: >=3.8
